face_parser/__init__.py
face_parser/parser.py
parser/__init__.py
parser/parser.py
face_parser-0.0.5.dist-info/METADATA
face_parser-0.0.5.dist-info/WHEEL
face_parser-0.0.5.dist-info/top_level.txt
face_parser-0.0.5.dist-info/RECORD
