Metadata-Version: 2.1
Name: face-parser
Version: 0.0.5
Summary: A small package to turn dlib's facial landmarks into more interesting values
Home-page: https://github.com/balbatross/dlib-face-parser
Author: Ross Leitch
Author-email: ross@end-game.com
License: UNKNOWN
Platform: UNKNOWN
Classifier: Programming Language :: Python :: 3
Classifier: License :: OSI Approved :: MIT License
Classifier: Operating System :: OS Independent
Requires-Dist: scipy
Requires-Dist: numpy
Requires-Dist: imutils
